mischief_managed/__init__.py
mischief_managed/__main__.py
mischief_managed/handler.py
mischief_managed/variables.py
mischief_managed-1.0.1.dist-info/LICENSE
mischief_managed-1.0.1.dist-info/METADATA
mischief_managed-1.0.1.dist-info/WHEEL
mischief_managed-1.0.1.dist-info/entry_points.txt
mischief_managed-1.0.1.dist-info/top_level.txt
mischief_managed-1.0.1.dist-info/RECORD
