Metadata-Version: 2.1
Name: mischief-managed
Version: 1.0.1
Summary: Files outside any folder are made tidy/managed by putting inside folder based on their extension or date
Home-page: https://github.com/Help-a-Sloth/mischief-managed
Author: Hemant Singh
Maintainer: amifunny
License: UNKNOWN
Keywords: Quick Work,Productivity,Automation,CleanupFiles,Management,Tidy,Folder Manage
Platform: UNKNOWN
Classifier: Programming Language :: Python :: 3
Classifier: License :: OSI Approved :: MIT License
Classifier: Operating System :: OS Independent
